{"Instrument groups":"Strings","Instruments":"String instrument bow","Main part":"grip","Subpart":"winding","Trade name":"baleen (Mysticeti)","main used material":"0","Family":"Balaenidae","Genus":"Eubalaena","Species":"glacialis","Geographical zone":"-","average netto weight":"","average brutto weight blank":"","average raw wood equivalent":"","IUCN Red list of protected species":"","CITES regulation":"","Occurance":"","threat":"DD","cites":"DD","speciesNamesAndSyns":{},"allAccepted":["Eubalaena glacialis"],"treeCountries":{},"timeTrade":[[],[]],"timeListing":[],"timeIUCN":[{"year":"2008","code":"EN","text":"EN","category":"Endangered","type":"iucn","sciName":"Eubalaena glacialis"},{"year":"2012","code":"EN","text":"EN","category":"Endangered","type":"iucn","sciName":"Eubalaena glacialis"},{"year":"2018","code":"EN","text":"EN","category":"Endangered","type":"iucn","sciName":"Eubalaena glacialis"},{"year":"2020","code":"CR","text":"CR","category":"Critically Endangered","type":"iucn","sciName":"Eubalaena glacialis"}],"timeThreat":[],"timeExtent":["2008","2020"],"material":[{"Genus":"Eubalaena ","Species":"glacialis"}],"listings":{"Eubalaena glacialis":{"Id":11020,"Kingdom":"Animalia","Phylum":"Chordata","Class":"Mammalia","Order":"Cetacea","Family":"Balaenidae","Genus":"Eubalaena","Species":"glacialis","Subspecies":"","Scientific Name":"Eubalaena glacialis","Author":"(P. L. S. M\u00fcller, 1776)","Rank":"SPECIES","Listing":"I","Party":"","Listed under":"Eubalaena spp.","Full note":"**I** [GENUS listing Eubalaena spp.] Formerly included in Balaena spp.","# Full note":"","All_DistributionFullNames":"Bahamas,Belgium,Bermuda (United Kingdom),Canada,Faroe Islands,France,Germany,Greenland,Iceland,Ireland,Italy,Malta,Morocco,Netherlands,Norway,Portugal,Russian Federation,Saint Helena and Dependencies (United Kingdom),Spain,Svalbard and Jan Mayen Islands,United Kingdom of Great Britain and Northern Ireland,United States of America","All_DistributionISOCodes":"BS,BE,BM,CA,FO,FR,DE,GL,IS,IE,IT,MT,MA,NL,NO,PT,RU,SH,ES,SJ,GB,US","NativeDistributionFullNames":"Bahamas,Belgium,Bermuda (United Kingdom),Canada,Faroe Islands,France,Germany,Greenland,Iceland,Ireland,Italy,Malta,Morocco,Netherlands,Norway,Portugal,Russian Federation,Saint Helena and Dependencies (United Kingdom),Spain,Svalbard and Jan Mayen Islands,United Kingdom of Great Britain and Northern Ireland,United States of America","Introduced_Distribution":"","Introduced(?)_Distribution":"","Reintroduced_Distribution":"","Extinct_Distribution":"","Extinct(?)_Distribution":"","Distribution_Uncertain":""}}}